LbAdmin/CreateAllSpecs.py
LbAdmin/CreateLHCbLCGMetaSpec.py
LbAdmin/LbDeploymentUpdateSdb.py
LbAdmin/RpmRelease.py
LbAdmin/__init__.py
LbAdmin-0.0.15.dist-info/LICENSE
LbAdmin-0.0.15.dist-info/METADATA
LbAdmin-0.0.15.dist-info/WHEEL
LbAdmin-0.0.15.dist-info/entry_points.txt
LbAdmin-0.0.15.dist-info/top_level.txt
LbAdmin-0.0.15.dist-info/zip-safe
LbAdmin-0.0.15.dist-info/RECORD
